<?xml version="1.0" encoding="UTF-8" standalone="no"?>
<RoboticsAPIData version="3">
    <world>
        <gravitation x="0.0" y="0.0" z="9.81"/>
        <additionalInformation>
            <info key="UseAsBaseForJogging" type="java.lang.Boolean" value="true"/>
        </additionalInformation>
        <frame id="_fe09a00c-ac9a-4582-8e46-324424ff9856" name="DrivePos">
            <transformation a="0.9452114246805668" b="0.00510853677504222" c="-3.139501826844158" x="10.935389425175797" y="-451.4688320594969" z="376.2847982239901"/>
            <additionalInformation>
                <info key="LastModificationTime" type="java.lang.Long" value="1500297520541"/>
                <info base="LBR_iiwa_14_R820_1" controller="KUKA_Sunrise_Cabinet_1" device="LBR_iiwa_14_R820_1" tcpName="Flange" tool="Flange" type="com.kuka.roboticsAPI.deviceModel.TeachInformation">
                    <tcpTransformation a="0.0" b="0.0" c="0.0" x="0.0" y="0.0" z="0.0"/>
                </info>
            </additionalInformation>
            <redundancyData>
                <redundancy transformationProviderName="KUKA_Sunrise_Cabinet_1/LBR_iiwa_14_R820_1" type="com.kuka.roboticsAPI.deviceModel.LBRE1Redundancy">
                    <info type="com.kuka.roboticsAPI.deviceModel.StatusTurnRedundancy$StatusParameter" value="2" valueType="java.lang.Integer"/>
                    <info type="com.kuka.roboticsAPI.deviceModel.StatusTurnRedundancy$TurnParameter" value="25" valueType="java.lang.Integer"/>
                    <info type="com.kuka.roboticsAPI.deviceModel.LBRE1Redundancy$E1Parameter" value="0.01805123872193497" valueType="java.lang.Double"/>
                </redundancy>
            </redundancyData>
        </frame>
        <frame id="_a5779651-e9e6-434a-bfcc-28e8788a7296" name="P1">
            <transformation a="-0.13412128180656313" b="0.28522965717257065" c="3.1005489568025597" x="-817.0009362108827" y="-128.47082844256084" z="75.00999956637969"/>
            <additionalInformation>
                <info key="LastModificationTime" type="java.lang.Long" value="1698008351909"/>
                <info base="LBR_iiwa_14_R820_1" controller="KUKA_Sunrise_Cabinet_1" device="LBR_iiwa_14_R820_1" tcpName="RobotiqGripper/TCP" tool="RobotiqGripper" type="com.kuka.roboticsAPI.deviceModel.TeachInformation">
                    <tcpTransformation a="0.0" b="0.0" c="0.0" x="0.0" y="0.0" z="244.0"/>
                </info>
            </additionalInformation>
            <redundancyData>
                <redundancy transformationProviderName="KUKA_Sunrise_Cabinet_1/LBR_iiwa_14_R820_1" type="com.kuka.roboticsAPI.deviceModel.LBRE1Redundancy">
                    <info type="com.kuka.roboticsAPI.deviceModel.StatusTurnRedundancy$StatusParameter" value="2" valueType="java.lang.Integer"/>
                    <info type="com.kuka.roboticsAPI.deviceModel.StatusTurnRedundancy$TurnParameter" value="25" valueType="java.lang.Integer"/>
                    <info type="com.kuka.roboticsAPI.deviceModel.LBRE1Redundancy$E1Parameter" value="0.005238364676258049" valueType="java.lang.Double"/>
                </redundancy>
            </redundancyData>
        </frame>
        <frame id="_508d02e5-23b2-4085-9f73-308812068da9" name="P2">
            <transformation a="-0.13407920783428015" b="0.28525070717854567" c="3.100696752970031" x="-764.1103656652367" y="-128.43657547096038" z="49.78289249167992"/>
            <additionalInformation>
                <info key="LastModificationTime" type="java.lang.Long" value="1698008522377"/>
                <info base="LBR_iiwa_14_R820_1" controller="KUKA_Sunrise_Cabinet_1" device="LBR_iiwa_14_R820_1" tcpName="RobotiqGripper/TCP" tool="RobotiqGripper" type="com.kuka.roboticsAPI.deviceModel.TeachInformation">
                    <tcpTransformation a="0.0" b="0.0" c="0.0" x="0.0" y="0.0" z="244.0"/>
                </info>
            </additionalInformation>
            <redundancyData>
                <redundancy transformationProviderName="KUKA_Sunrise_Cabinet_1/LBR_iiwa_14_R820_1" type="com.kuka.roboticsAPI.deviceModel.LBRE1Redundancy">
                    <info type="com.kuka.roboticsAPI.deviceModel.StatusTurnRedundancy$StatusParameter" value="2" valueType="java.lang.Integer"/>
                    <info type="com.kuka.roboticsAPI.deviceModel.StatusTurnRedundancy$TurnParameter" value="25" valueType="java.lang.Integer"/>
                    <info type="com.kuka.roboticsAPI.deviceModel.LBRE1Redundancy$E1Parameter" value="0.005145846408856003" valueType="java.lang.Double"/>
                </redundancy>
            </redundancyData>
        </frame>
        <frame id="_41189241-1858-4c1f-ab72-f35d2c700266" name="P3">
            <transformation a="-0.11775028699125209" b="0.01814952014684559" c="3.1049281759804743" x="-797.0324606988752" y="-109.28697228299363" z="102.96013315899808"/>
            <additionalInformation>
                <info key="LastModificationTime" type="java.lang.Long" value="1698006738729"/>
                <info base="LBR_iiwa_14_R820_1" controller="KUKA_Sunrise_Cabinet_1" device="LBR_iiwa_14_R820_1" tcpName="RobotiqGripper/TCP" tool="RobotiqGripper" type="com.kuka.roboticsAPI.deviceModel.TeachInformation">
                    <tcpTransformation a="0.0" b="0.0" c="0.0" x="0.0" y="0.0" z="244.0"/>
                </info>
            </additionalInformation>
            <redundancyData>
                <redundancy transformationProviderName="KUKA_Sunrise_Cabinet_1/LBR_iiwa_14_R820_1" type="com.kuka.roboticsAPI.deviceModel.LBRE1Redundancy">
                    <info type="com.kuka.roboticsAPI.deviceModel.StatusTurnRedundancy$StatusParameter" value="2" valueType="java.lang.Integer"/>
                    <info type="com.kuka.roboticsAPI.deviceModel.StatusTurnRedundancy$TurnParameter" value="13" valueType="java.lang.Integer"/>
                    <info type="com.kuka.roboticsAPI.deviceModel.LBRE1Redundancy$E1Parameter" value="-0.5211013630276692" valueType="java.lang.Double"/>
                </redundancy>
            </redundancyData>
        </frame>
        <frame id="_225c3578-3605-4812-84ac-72c98db15085" name="P4">
            <transformation a="-0.11775026414481898" b="0.018149383291013798" c="3.1049281400104163" x="-797.0324080662831" y="-109.28700064145187" z="102.96012860906256"/>
            <additionalInformation>
                <info key="LastModificationTime" type="java.lang.Long" value="1698006740522"/>
                <info base="LBR_iiwa_14_R820_1" controller="KUKA_Sunrise_Cabinet_1" device="LBR_iiwa_14_R820_1" tcpName="RobotiqGripper/TCP" tool="RobotiqGripper" type="com.kuka.roboticsAPI.deviceModel.TeachInformation">
                    <tcpTransformation a="0.0" b="0.0" c="0.0" x="0.0" y="0.0" z="244.0"/>
                </info>
            </additionalInformation>
            <redundancyData>
                <redundancy transformationProviderName="KUKA_Sunrise_Cabinet_1/LBR_iiwa_14_R820_1" type="com.kuka.roboticsAPI.deviceModel.LBRE1Redundancy">
                    <info type="com.kuka.roboticsAPI.deviceModel.StatusTurnRedundancy$StatusParameter" value="2" valueType="java.lang.Integer"/>
                    <info type="com.kuka.roboticsAPI.deviceModel.StatusTurnRedundancy$TurnParameter" value="13" valueType="java.lang.Integer"/>
                    <info type="com.kuka.roboticsAPI.deviceModel.LBRE1Redundancy$E1Parameter" value="-0.5211013030319761" valueType="java.lang.Double"/>
                </redundancy>
            </redundancyData>
        </frame>
        <frame id="_cfc4a2fb-ffc2-4e09-99d5-849a06490a8c" name="P5">
            <transformation a="-0.7012150440835101" b="0.027415902204424525" c="3.1054728522515265" x="-604.5117196673926" y="-115.0067595704962" z="120.75850808078647"/>
            <additionalInformation>
                <info key="LastModificationTime" type="java.lang.Long" value="1698007680483"/>
                <info base="LBR_iiwa_14_R820_1" controller="KUKA_Sunrise_Cabinet_1" device="LBR_iiwa_14_R820_1" tcpName="RobotiqGripper/TCP" tool="RobotiqGripper" type="com.kuka.roboticsAPI.deviceModel.TeachInformation">
                    <tcpTransformation a="0.0" b="0.0" c="0.0" x="0.0" y="0.0" z="244.0"/>
                </info>
            </additionalInformation>
            <redundancyData>
                <redundancy transformationProviderName="KUKA_Sunrise_Cabinet_1/LBR_iiwa_14_R820_1" type="com.kuka.roboticsAPI.deviceModel.LBRE1Redundancy">
                    <info type="com.kuka.roboticsAPI.deviceModel.StatusTurnRedundancy$StatusParameter" value="2" valueType="java.lang.Integer"/>
                    <info type="com.kuka.roboticsAPI.deviceModel.StatusTurnRedundancy$TurnParameter" value="13" valueType="java.lang.Integer"/>
                    <info type="com.kuka.roboticsAPI.deviceModel.LBRE1Redundancy$E1Parameter" value="-0.5209739107953747" valueType="java.lang.Double"/>
                </redundancy>
            </redundancyData>
        </frame>
        <frame id="_baca8bcb-29f5-46b5-8238-e9bb59c3756a" name="P6">
            <transformation a="-1.2406717064366022" b="0.02732667088830901" c="3.1054867837111346" x="-583.0924006936546" y="106.06582456980573" z="160.14211787245674"/>
            <additionalInformation>
                <info key="LastModificationTime" type="java.lang.Long" value="1698007745083"/>
                <info base="LBR_iiwa_14_R820_1" controller="KUKA_Sunrise_Cabinet_1" device="LBR_iiwa_14_R820_1" tcpName="RobotiqGripper/TCP" tool="RobotiqGripper" type="com.kuka.roboticsAPI.deviceModel.TeachInformation">
                    <tcpTransformation a="0.0" b="0.0" c="0.0" x="0.0" y="0.0" z="244.0"/>
                </info>
            </additionalInformation>
            <redundancyData>
                <redundancy transformationProviderName="KUKA_Sunrise_Cabinet_1/LBR_iiwa_14_R820_1" type="com.kuka.roboticsAPI.deviceModel.LBRE1Redundancy">
                    <info type="com.kuka.roboticsAPI.deviceModel.StatusTurnRedundancy$StatusParameter" value="2" valueType="java.lang.Integer"/>
                    <info type="com.kuka.roboticsAPI.deviceModel.StatusTurnRedundancy$TurnParameter" value="13" valueType="java.lang.Integer"/>
                    <info type="com.kuka.roboticsAPI.deviceModel.LBRE1Redundancy$E1Parameter" value="-0.5210433593007239" valueType="java.lang.Double"/>
                </redundancy>
            </redundancyData>
        </frame>
    </world>
    <objectTemplates>
        <toolTemplate class="" name="NoLoad">
            <frames>
                <frame id="_5d382cd1-bcdd-4ce5-9ef7-ff979be52947" name="TCP1">
                    <transformation a="0.0" b="0.0" c="0.0" x="540.0" y="-315.0" z="0.0"/>
                    <additionalInformation>
                        <info key="Radius" type="java.lang.Integer" value="25"/>
                        <info key="SafetyID" type="java.lang.Integer" value="0"/>
                    </additionalInformation>
                </frame>
                <frame id="_e5b06d4f-a992-4acb-8f04-fcc3648d9691" name="TCP2">
                    <transformation a="0.0" b="0.0" c="0.0" x="540.0" y="315.0" z="0.0"/>
                    <additionalInformation>
                        <info key="Radius" type="java.lang.Integer" value="25"/>
                        <info key="SafetyID" type="java.lang.Integer" value="3"/>
                    </additionalInformation>
                </frame>
                <frame id="_ec562d38-61f2-4c24-a197-0de55e49ce2f" name="TCP4">
                    <transformation a="0.0" b="0.0" c="0.0" x="-540.0" y="315.0" z="0.0"/>
                    <additionalInformation>
                        <info key="Radius" type="java.lang.Integer" value="25"/>
                        <info key="SafetyID" type="java.lang.Integer" value="2"/>
                    </additionalInformation>
                </frame>
                <frame id="_2fad5e82-ce67-477d-8e43-5265331a183a" name="TCP3">
                    <transformation a="0.0" b="0.0" c="0.0" x="-540.0" y="-315.0" z="0.0"/>
                    <additionalInformation>
                        <info key="Radius" type="java.lang.Integer" value="25"/>
                        <info key="SafetyID" type="java.lang.Integer" value="1"/>
                    </additionalInformation>
                </frame>
            </frames>
            <additionalInformation>
                <info key="SafetyID" type="java.lang.Integer" value="0"/>
                <info key="Comment" type="java.lang.String" value="Corner 1 of the AGV where the tool-related-velocity will be monitored if the PLC sends the signal to activate this corner."/>
                <info key="ToolVelocityPointPath" type="java.lang.String" value="/TCP3"/>
                <info key="ToolVelocityPointPath" type="java.lang.String" value="/TCP2"/>
                <info key="ToolVelocityPointPath" type="java.lang.String" value="/TCP4"/>
                <info key="ToolVelocityPointPath" type="java.lang.String" value="/TCP1"/>
                <info key="ID" type="java.lang.String" value="fcebf5cb-7e23-4d6f-879e-74efecb9875f"/>
            </additionalInformation>
            <loadData cogA="0.0" cogB="0.0" cogC="0.0" cogX="0.0" cogY="0.0" cogZ="0.0" inertiaX="0.0" inertiaY="0.0" inertiaZ="0.0" mass="0.0"/>
        </toolTemplate>
        <toolTemplate class="" name="Load">
            <frames>
                <frame id="_4e48e470-f674-4608-af7a-974d9feeb469" name="TCP1">
                    <transformation a="0.0" b="0.0" c="0.0" x="540.0" y="-315.0" z="0.0"/>
                    <additionalInformation>
                        <info key="Radius" type="java.lang.Integer" value="25"/>
                        <info key="SafetyID" type="java.lang.Integer" value="3"/>
                    </additionalInformation>
                </frame>
                <frame id="_40bfa844-5b70-47e7-bb84-fcace9cf0ad4" name="TCP2">
                    <transformation a="0.0" b="0.0" c="0.0" x="540.0" y="315.0" z="0.0"/>
                    <additionalInformation>
                        <info key="Radius" type="java.lang.Integer" value="25"/>
                        <info key="SafetyID" type="java.lang.Integer" value="2"/>
                    </additionalInformation>
                </frame>
                <frame id="_537dbe05-1d2f-43ac-82f8-ab04bccb5bb5" name="TCP4">
                    <transformation a="0.0" b="0.0" c="0.0" x="-540.0" y="315.0" z="0.0"/>
                    <additionalInformation>
                        <info key="Radius" type="java.lang.Integer" value="25"/>
                        <info key="SafetyID" type="java.lang.Integer" value="0"/>
                    </additionalInformation>
                </frame>
                <frame id="_4609f686-f9d4-42f1-81bc-03490573f198" name="TCP3">
                    <transformation a="0.0" b="0.0" c="0.0" x="-540.0" y="-315.0" z="0.0"/>
                    <additionalInformation>
                        <info key="Radius" type="java.lang.Integer" value="25"/>
                        <info key="SafetyID" type="java.lang.Integer" value="1"/>
                    </additionalInformation>
                </frame>
            </frames>
            <additionalInformation>
                <info key="Comment" type="java.lang.String" value="Corner 1 of the AGV where the tool-related-velocity will be monitored if the PLC sends the signal to activate this corner."/>
                <info key="SafetyID" type="java.lang.Integer" value="1"/>
                <info key="ToolVelocityPointPath" type="java.lang.String" value="/TCP3"/>
                <info key="ToolVelocityPointPath" type="java.lang.String" value="/TCP2"/>
                <info key="ToolVelocityPointPath" type="java.lang.String" value="/TCP4"/>
                <info key="ToolVelocityPointPath" type="java.lang.String" value="/TCP1"/>
                <info key="ID" type="java.lang.String" value="425455b8-4883-476a-9967-396432325126"/>
            </additionalInformation>
            <loadData cogA="0.0" cogB="0.0" cogC="0.0" cogX="0.0" cogY="0.0" cogZ="0.0" inertiaX="0.0" inertiaY="0.0" inertiaZ="0.0" mass="0.0"/>
        </toolTemplate>
        <workpieceTemplate class="" name="WorkpieceTemplate">
            <frames>
                <frame id="_b0712bee-cb71-43d2-8d6f-8bf8a5b6e4dd" name="Frame">
                    <transformation a="0.0" b="0.0" c="0.0" x="0.0" y="0.0" z="0.0"/>
                </frame>
            </frames>
            <loadData cogA="0.0" cogB="0.0" cogC="0.0" cogX="0.0" cogY="0.0" cogZ="0.0" inertiaX="0.0" inertiaY="0.0" inertiaZ="0.0" mass="0.0"/>
        </workpieceTemplate>
        <toolTemplate class="" defaultMotionFrameRef="/TCP" name="RobotiqGripper">
            <frames>
                <frame id="_68b67f61-2686-4d31-b829-f5b56bded6df" name="TCP">
                    <transformation a="0.0" b="0.0" c="0.0" x="0.0" y="0.0" z="244.0"/>
                </frame>
            </frames>
            <additionalInformation>
                <info key="ID" type="java.lang.String" value="80c59157-b533-4747-8456-dd4948d16563"/>
            </additionalInformation>
            <loadData cogA="0.0" cogB="0.0" cogC="0.0" cogX="0.0" cogY="0.0" cogZ="0.0" inertiaX="0.0" inertiaY="0.0" inertiaZ="0.0" mass="0.0"/>
        </toolTemplate>
    </objectTemplates>
</RoboticsAPIData>
